certifi-stubs/METADATA.toml
certifi-stubs/__init__.pyi
types_certifi-2021.10.8.2.dist-info/METADATA
types_certifi-2021.10.8.2.dist-info/WHEEL
types_certifi-2021.10.8.2.dist-info/top_level.txt
types_certifi-2021.10.8.2.dist-info/RECORD
