Metadata-Version: 2.1
Name: types-certifi
Version: 2021.10.8.2
Summary: Typing stubs for certifi
Home-page: https://github.com/python/typeshed
License: Apache-2.0 license
Project-URL: GitHub, https://github.com/python/typeshed
Project-URL: Changes, https://github.com/typeshed-internal/stub_uploader/blob/main/data/changelogs/certifi.md
Project-URL: Issue tracker, https://github.com/python/typeshed/issues
Project-URL: Chat, https://gitter.im/python/typing
Platform: UNKNOWN
Classifier: License :: OSI Approved :: Apache Software License
Classifier: Typing :: Stubs Only
